netbox_initializers/__init__.py
netbox_initializers/version.py
netbox_initializers/initializers/__init__.py
netbox_initializers/initializers/aggregates.py
netbox_initializers/initializers/asns.py
netbox_initializers/initializers/base.py
netbox_initializers/initializers/cables.py
netbox_initializers/initializers/circuit_types.py
netbox_initializers/initializers/circuits.py
netbox_initializers/initializers/cluster_groups.py
netbox_initializers/initializers/cluster_types.py
netbox_initializers/initializers/clusters.py
netbox_initializers/initializers/config_contexts.py
netbox_initializers/initializers/config_templates.py
netbox_initializers/initializers/contact_groups.py
netbox_initializers/initializers/contact_roles.py
netbox_initializers/initializers/contacts.py
netbox_initializers/initializers/custom_fields.py
netbox_initializers/initializers/custom_links.py
netbox_initializers/initializers/device_roles.py
netbox_initializers/initializers/device_types.py
netbox_initializers/initializers/devices.py
netbox_initializers/initializers/groups.py
netbox_initializers/initializers/interfaces.py
netbox_initializers/initializers/ip_addresses.py
netbox_initializers/initializers/locations.py
netbox_initializers/initializers/macs.py
netbox_initializers/initializers/manufacturers.py
netbox_initializers/initializers/object_permissions.py
netbox_initializers/initializers/platforms.py
netbox_initializers/initializers/power_feeds.py
netbox_initializers/initializers/power_panels.py
netbox_initializers/initializers/prefix_vlan_roles.py
netbox_initializers/initializers/prefixes.py
netbox_initializers/initializers/primary_ips.py
netbox_initializers/initializers/providers.py
netbox_initializers/initializers/rack_roles.py
netbox_initializers/initializers/rack_types.py
netbox_initializers/initializers/racks.py
netbox_initializers/initializers/regions.py
netbox_initializers/initializers/rirs.py
netbox_initializers/initializers/route_targets.py
netbox_initializers-4.4.0.dist-info/METADATA
netbox_initializers-4.4.0.dist-info/WHEEL
netbox_initializers-4.4.0.dist-info/licenses/LICENSE
netbox_initializers-4.4.0.dist-info/RECORD
