Metadata-Version: 2.4
Name: netbox-initializers
Version: 4.4.0
Summary: Load initial data into Netbox
Project-URL: repository, https://github.com/tobiasge/netbox-initializers
Project-URL: issues, https://github.com/tobiasge/netbox-initializers/issues
Project-URL: releasenotes, https://github.com/tobiasge/netbox-initializers/releases
Author-email: Tobias Genannt <tobias.genannt@gmail.com>
License-Expression: Apache-2.0
License-File: LICENSE
Classifier: Environment :: Plugins
Classifier: Framework :: Django
Classifier: Topic :: System :: Networking
Classifier: Topic :: System :: Systems Administration
Requires-Python: >=3.10
Requires-Dist: ruamel-yaml>=0.18.10
